django_components_storybook/apps.py
django_components_storybook/urls.py
django_components_storybook/views.py
django_components_storybook-0.0.1.dist-info/LICENSE
django_components_storybook-0.0.1.dist-info/METADATA
django_components_storybook-0.0.1.dist-info/WHEEL
django_components_storybook-0.0.1.dist-info/top_level.txt
django_components_storybook-0.0.1.dist-info/RECORD
